[
  {"name": "Vintage Comic Book", "value": 45},
  {"name": "Rusty Lawn Mower", "value": 3},
  {"name": "Limited Edition Sneakers", "value": 78},
  {"name": "Solid Gold Toothpick", "value": 2},
  {"name": "Ancient Egyptian Scarab", "value": 92},
  {"name": "Expired Yogurt", "value": 1},
  {"name": "First Edition Charizard", "value": 88},
  {"name": "Mystery Box (unopened)", "value": 34},
  {"name": "Haunted Portrait", "value": 12},
  {"name": "Diamond-Encrusted Watch", "value": 95},
  {"name": "Slightly Used Tissue", "value": 0},
  {"name": "Moon Rock Fragment", "value": 67},
  {"name": "Signed Baseball (authenticated)", "value": 82},
  {"name": "Pet Rock with Googly Eyes", "value": 4},
  {"name": "Antique Map of Atlantis", "value": 55},
  {"name": "Strange Smelling Jar", "value": 8},
  {"name": "Original Picasso Sketch", "value": 99},
  {"name": "Bag of Mystery Chips", "value": 5},
  {"name": "Medieval Knight's Helmet", "value": 61},
  {"name": "Broken Fidget Spinner", "value": 2},
  {"name": "Rare Blue Lobster", "value": 41},
  {"name": "Box of Assorted Buttons", "value": 6},
  {"name": "Alien Communication Device", "value": 73},
  {"name": "Slightly Chipped Mug", "value": 7},
  {"name": "Stuffed Unicorn (giant)", "value": 28},
  {"name": "Vinyl Record (unknown artist)", "value": 19},
  {"name": "Time Travel Pamphlet", "value": 11},
  {"name": "Crystal Ball (cloudy)", "value": 36},
  {"name": "Vintage Typewriter", "value": 52},
  {"name": "Mysterious Glowing Orb", "value": 44},
  {"name": "Self-Porting Novel", "value": 22},
  {"name": "Taxidermied Squirrel", "value": 18},
  {"name": "Rare Plant (possibly extinct)", "value": 71},
  {"name": "Belt Buckle Collection", "value": 9},
  {"name": "Antique Compass (broken)", "value": 14},
  {"name": "Space Program Patch Set", "value": 58},
  {"name": "Box of Vintage Keys", "value": 25},
  {"name": "Haunted Doll (friendly)", "value": 31},
  {"name": "Original Recipe Scroll", "value": 49},
  {"name": "Meteorite Slice", "value": 64},
  {"name": "Inflatable Crown", "value": 3},
  {"name": "Handwritten Love Letter", "value": 27},
  {"name": "Ancient Coins (10 pack)", "value": 76},
  {"name": "Mystery Meat Can", "value": 4},
  {"name": "World's Smallest Violin", "value": 16},
  {"name": "Shrunken Head (replica)", "value": 39},
  {"name": "Fossilized Dinosaur Tooth", "value": 69},
  {"name": "Novelty Giant Check", "value": 10},
  {"name": "Rare Stamps Collection", "value": 84},
  {"name": "Lucky Rabbit's Foot", "value": 13},
  {"name": "Pirate Treasure Map", "value": 47},
  {"name": "Singing Fish Plaque", "value": 8},
  {"name": "Antique Medical Kit", "value": 56},
  {"name": "Glitter Bomb (unopened)", "value": 15},
  {"name": "Vintage Camera (working)", "value": 62},
  {"name": "Collection of Odd Socks", "value": 5},
  {"name": "Royal Crown Replica", "value": 37},
  {"name": "Sword in the Stone (mini)", "value": 29},
  {"name": "Vinyl - Beatles White Album", "value": 89},
  {"name": "Mystery Flavor Jellybeans", "value": 17},
  {"name": "Telescope from 1800s", "value": 53},
  {"name": "Lava Lamp (vintage)", "value": 24},
  {"name": "Diving Helmet", "value": 48},
  {"name": "Bag of Magic Beans", "value": 21},
  {"name": "Victrola Phonograph", "value": 65},
  {"name": "Rattlesnake in a Jar", "value": 33},
  {"name": "Enigma Machine Replica", "value": 74},
  {"name": "Velvet Painting", "value": 20},
  {"name": "Ship in a Bottle", "value": 42},
  {"name": "Robot Dog (vintage)", "value": 38},
  {"name": "Collection of Fortunes", "value": 6},
  {"name": "Stradivarius (allegedly)", "value": 91},
  {"name": "Rubber Chicken", "value": 11},
  {"name": "Antique Globe", "value": 59},
  {"name": "Monster Under Bed Kit", "value": 14},
  {"name": "Autographed Celebrity Napkin", "value": 46},
  {"name": "Cuckoo Clock (suspicious)", "value": 35},
  {"name": "Box of Unopened Beanie Babies", "value": 51},
  {"name": "Mystery Novel (last page torn)", "value": 23},
  {"name": "Victorian Era Lockpick Set", "value": 57},
  {"name": "Clown Painting", "value": 9},
  {"name": "Rare Pokemon Card (holo)", "value": 80},
  {"name": "Desk Organizer (haunted)", "value": 26},
  {"name": "Vintage Slot Machine", "value": 72},
  {"name": "Fake Mustache Collection", "value": 7},
  {"name": "Maritime Spyglass", "value": 54},
  {"name": "Scented Candle (mystery)", "value": 12},
  {"name": "Original Star Wars Script", "value": 86},
  {"name": "Tiny House for Gnomes", "value": 19},
  {"name": "Antique Chess Set", "value": 63},
  {"name": "Bag of Sand from Mars", "value": 40},
  {"name": "Victorian Mourning Jewelry", "value": 50},
  {"name": "Novelty Giant Pen", "value": 4},
  {"name": "Rare Butterfly Specimen", "value": 66},
  {"name": "Mystery Subscription Box", "value": 30},
  {"name": "Shakespeare First Folio", "value": 97},
  {"name": "Glow-in-Dark Skeleton", "value": 18},
  {"name": "Vintage Wurlitzer Jukebox", "value": 79},
  {"name": "Box of 1000 Paperclips", "value": 2},
  {"name": "Rare Orchid", "value": 68},
  {"name": "Telegram from 1920", "value": 43},
  {"name": "Inflatable Pool Dinosaur", "value": 16},
  {"name": "Antique Microscope", "value": 70},
  {"name": "Mystery Meat Jerky", "value": 10},
  {"name": "Vintage Pinball Machine", "value": 75},
  {"name": "Collection of Snow Globes", "value": 32},
  {"name": "Original Patent Document", "value": 60},
  {"name": "Novelty Inflatable Cactus", "value": 5},
  {"name": "Rare Tarot Deck", "value": 45},
  {"name": "Victorian Era Dentures", "value": 8},
  {"name": "Vintage Arcade Cabinet", "value": 77},
  {"name": "Mystery Spice Jar", "value": 13},
  {"name": "Antique Quill Pen Set", "value": 39},
  {"name": "Taxidermied Owl", "value": 28},
  {"name": "Rare Vinyl - Elvis", "value": 85},
  {"name": "Box of Mystery Bones", "value": 15},
  {"name": "Vintage Boxing Gloves", "value": 48},
  {"name": "Lucky Horseshoe", "value": 22},
  {"name": "Rare Mineral Specimen", "value": 58},
  {"name": "Mystery Perfume Bottle", "value": 17},
  {"name": "Antique Barber Chair", "value": 64},
  {"name": "Novelty Whoopee Cushion", "value": 3},
  {"name": "Vintage Nurse's Cap", "value": 24},
  {"name": "Rare Butterfly Net", "value": 36},
  {"name": "Mystery Tea Set", "value": 31},
  {"name": "Original Political Cartoon", "value": 52},
  {"name": "Box of Vintage Postcards", "value": 44},
  {"name": "Antique Fire Extinguisher", "value": 41},
  {"name": "Novelty Groucho Glasses", "value": 6},
  {"name": "Vintage Gas Mask", "value": 35},
  {"name": "Rare Insect Collection", "value": 56},
  {"name": "Mystery Jelly Jar", "value": 11},
  {"name": "Original Wanted Poster", "value": 49},
  {"name": "Antique Dentist Chair", "value": 67},
  {"name": "Box of Seashells", "value": 14},
  {"name": "Vintage Bowling Ball", "value": 29}
]
